dftfit/__init__.py
dftfit/__main__.py
dftfit/batch.py
dftfit/config.py
dftfit/data.py
dftfit/dftfit.py
dftfit/logging.py
dftfit/objective.py
dftfit/optimize.py
dftfit/parameter.py
dftfit/problem.py
dftfit/properties.py
dftfit/training.py
dftfit/utils.py
dftfit/visualize.py
dftfit/cli/__init__.py
dftfit/cli/db.py
dftfit/cli/test.py
dftfit/cli/train.py
dftfit/cli/utils.py
dftfit/db/__init__.py
dftfit/db/actions.py
dftfit/db/query.py
dftfit/db/table.py
dftfit/io/__init__.py
dftfit/io/base.py
dftfit/io/espresso.py
dftfit/io/lammps.py
dftfit/io/lammps_cython.py
dftfit/io/mattoolkit.py
dftfit/io/minimal.py
dftfit/io/siesta.py
dftfit/io/utils.py
dftfit/io/vasp.py
dftfit/potential/__init__.py
dftfit/potential/models.py
dftfit/potential/representation.py
dftfit/predict/__init__.py
dftfit/predict/base.py
dftfit/predict/utils.py
dftfit/schema/__init__.py
dftfit/schema/base.py
dftfit/schema/configuration.py
dftfit/schema/fields.py
dftfit/schema/potential.py
dftfit/schema/properties.py
dftfit/schema/training.py
dftfit-0.5.0.dist-info/METADATA
dftfit-0.5.0.dist-info/RECORD
dftfit-0.5.0.dist-info/WHEEL
dftfit-0.5.0.dist-info/entry_points.txt
dftfit-0.5.0.dist-info/top_level.txt
tests/io/__init__.py
tests/io/test_lammps.py
tests/io/test_lammps_cython.py
tests/io/test_mattoolkit.py
tests/io/test_siesta.py
tests/io/test_vasp.py
