Metadata-Version: 2.1
Name: dftfit
Version: 0.5.0
Summary: Ab-Initio Molecular Dynamics Potential Development
Home-page: https://gitlab.com/costrouc/dftfit
Author: Chris Ostrouchov
Author-email: chris.ostrouchov+dftfit@gmail.com
License: MIT
Download-URL: https://gitlab.com/costrouc/dftfit/repository/archive.zip?ref=v0.5.0
Keywords: materials dft molecular dynamics lammps science hpc
Platform: UNKNOWN
Classifier: Development Status :: 4 - Beta
Classifier: Natural Language :: English
Classifier: License :: OSI Approved :: MIT License
Classifier: Programming Language :: Python :: 3.6
Classifier: Programming Language :: Python :: 3.7
Provides-Extra: mattoolkit
Requires-Dist: pymatgen
Requires-Dist: marshmallow
Requires-Dist: pyyaml
Requires-Dist: pygmo
Requires-Dist: pandas
Requires-Dist: scipy
Requires-Dist: numpy
Requires-Dist: scikit-learn
Requires-Dist: lammps-cython
Requires-Dist: pymatgen-lammps
Provides-Extra: mattoolkit
Requires-Dist: mattoolkit; extra == 'mattoolkit'
